ukincomecalculator/__init__.py
ukincomecalculator/calculator.py
ukincomecalculator-0.2.dist-info/METADATA
ukincomecalculator-0.2.dist-info/WHEEL
ukincomecalculator-0.2.dist-info/licenses/LICENSE.txt
ukincomecalculator-0.2.dist-info/RECORD
