Metadata-Version: 2.4
Name: ukincomecalculator
Version: 0.2
Summary: A Python Package that calculate take home income for UK Employees
Project-URL: Documentation, https://github.com/Hifeoluwa14/ukincomecalculator#readme
Author-email: Hifeoluwa14 <ifeoluwaojeleye.o@gmail.com>
License-Expression: MIT
License-File: LICENSE.txt
Classifier: Development Status :: 4 - Beta
Classifier: Programming Language :: Python
Classifier: Programming Language :: Python :: 3.8
Classifier: Programming Language :: Python :: 3.9
Classifier: Programming Language :: Python :: 3.10
Classifier: Programming Language :: Python :: 3.11
Classifier: Programming Language :: Python :: 3.12
Requires-Python: >=3.8
